keylib/__init__.py
keylib_MGGY8411_yy2205-0.1.0.dist-info/METADATA
keylib_MGGY8411_yy2205-0.1.0.dist-info/WHEEL
keylib_MGGY8411_yy2205-0.1.0.dist-info/top_level.txt
keylib_MGGY8411_yy2205-0.1.0.dist-info/RECORD
