Metadata-Version: 2.1
Name: keylib-MGGY8411-yy2205
Version: 0.1.0
Summary: Just a key
Author: Yue
Author-email: yy2205@nyu.edu
